MANIFEST.in
README.txt
setup.cfg
setup.py
airship_python/__init__.py
airship_python.egg-info/PKG-INFO
airship_python.egg-info/SOURCES.txt
airship_python.egg-info/dependency_links.txt
airship_python.egg-info/requires.txt
airship_python.egg-info/top_level.txt